[
{
"comment":"OneMinuteFocusExposure",
"filter":"u",
"seqtot":61,
"seqnum":1,
"seqid":"2022B",
"expType":"object",
"object":"1minexp_000",
"proposer":"Leauthaud",
"program":"Merian",
"RA":18.41884,
"propid":"2020B-0288",
"dec":-59.65974,
"expTime":60.0,
"count":1,
"wait":"False"
},
{
"comment":"--",
"filter":"u",
"seqtot":61,
"seqnum":2,
"seqid":"2022B",
"expType":"object",
"object":"TIC206544316_J011340.52-593935.06_u",
"proposer":"Leauthaud",
"program":"Merian",
"RA":18.41884,
"propid":"2020B-0288",
"dec":-59.65974,
"expTime":5.0,
"count":1,
"wait":"False"
},
{
"comment":"--",
"filter":"u",
"seqtot":61,
"seqnum":3,
"seqid":"2022B",
"expType":"object",
"object":"TIC206544316_J011329.01-594413.82_u",
"proposer":"Leauthaud",
"program":"Merian",
"RA":18.3708804381,
"propid":"2020B-0288",
"dec":-59.7371724401,
"expTime":5.0,
"count":1,
"wait":"False"
},
{
"comment":"--",
"filter":"u",
"seqtot":61,
"seqnum":4,
"seqid":"2022B",
"expType":"object",
"object":"TIC206544316_J011340.27-594417.31_u",
"proposer":"Leauthaud",
"program":"Merian",
"RA":18.4178271845,
"propid":"2020B-0288",
"dec":-59.738141809,
"expTime":5.0,
"count":1,
"wait":"False"
},
{
"comment":"--",
"filter":"u",
"seqtot":61,
"seqnum":5,
"seqid":"2022B",
"expType":"object",
"object":"TIC206544316_J011358.09-594221.65_u",
"proposer":"Leauthaud",
"program":"Merian",
"RA":18.4920486603,
"propid":"2020B-0288",
"dec":-59.7060152095,
"expTime":5.0,
"count":1,
"wait":"False"
},
{
"comment":"--",
"filter":"u",
"seqtot":61,
"seqnum":6,
"seqid":"2022B",
"expType":"object",
"object":"TIC206544316_J011356.69-593441.05_u",
"proposer":"Leauthaud",
"program":"Merian",
"RA":18.4862440094,
"propid":"2020B-0288",
"dec":-59.5780696435,
"expTime":5.0,
"count":1,
"wait":"False"
},
{
"comment":"--",
"filter":"u",
"seqtot":61,
"seqnum":7,
"seqid":"2022B",
"expType":"object",
"object":"TIC206544316_J011347.10-594505.26_u",
"proposer":"Leauthaud",
"program":"Merian",
"RA":18.4462801192,
"propid":"2020B-0288",
"dec":-59.7514620663,
"expTime":5.0,
"count":1,
"wait":"False"
},
{
"comment":"--",
"filter":"u",
"seqtot":61,
"seqnum":8,
"seqid":"2022B",
"expType":"object",
"object":"TIC206544316_J011359.62-593638.66_u",
"proposer":"Leauthaud",
"program":"Merian",
"RA":18.4984426378,
"propid":"2020B-0288",
"dec":-59.6107401452,
"expTime":5.0,
"count":1,
"wait":"False"
},
{
"comment":"--",
"filter":"u",
"seqtot":61,
"seqnum":9,
"seqid":"2022B",
"expType":"object",
"object":"TIC206544316_J011350.54-594124.32_u",
"proposer":"Leauthaud",
"program":"Merian",
"RA":18.4605903166,
"propid":"2020B-0288",
"dec":-59.6900895528,
"expTime":5.0,
"count":1,
"wait":"False"
},
{
"comment":"--",
"filter":"u",
"seqtot":61,
"seqnum":10,
"seqid":"2022B",
"expType":"object",
"object":"TIC206544316_J011344.72-593353.66_u",
"proposer":"Leauthaud",
"program":"Merian",
"RA":18.4363661265,
"propid":"2020B-0288",
"dec":-59.5649061453,
"expTime":5.0,
"count":1,
"wait":"False"
},
{
"comment":"--",
"filter":"u",
"seqtot":61,
"seqnum":11,
"seqid":"2022B",
"expType":"object",
"object":"TIC206544316_J011335.55-594132.99_u",
"proposer":"Leauthaud",
"program":"Merian",
"RA":18.3981516618,
"propid":"2020B-0288",
"dec":-59.6924982452,
"expTime":5.0,
"count":1,
"wait":"False"
},
{
"comment":"--",
"filter":"u",
"seqtot":61,
"seqnum":12,
"seqid":"2022B",
"expType":"object",
"object":"TIC206544316_J011334.05-593759.16_u",
"proposer":"Leauthaud",
"program":"Merian",
"RA":18.3919089566,
"propid":"2020B-0288",
"dec":-59.6331023067,
"expTime":5.0,
"count":1,
"wait":"False"
},
{
"comment":"--",
"filter":"u",
"seqtot":61,
"seqnum":13,
"seqid":"2022B",
"expType":"object",
"object":"TIC206544316_J011343.82-593523.40_u",
"proposer":"Leauthaud",
"program":"Merian",
"RA":18.4326205931,
"propid":"2020B-0288",
"dec":-59.5898354735,
"expTime":5.0,
"count":1,
"wait":"False"
},
{
"comment":"--",
"filter":"u",
"seqtot":61,
"seqnum":14,
"seqid":"2022B",
"expType":"object",
"object":"TIC206544316_J011337.89-593427.42_u",
"proposer":"Leauthaud",
"program":"Merian",
"RA":18.4078896823,
"propid":"2020B-0288",
"dec":-59.5742859712,
"expTime":5.0,
"count":1,
"wait":"False"
},
{
"comment":"--",
"filter":"u",
"seqtot":61,
"seqnum":15,
"seqid":"2022B",
"expType":"object",
"object":"TIC206544316_J011403.65-593631.31_u",
"proposer":"Leauthaud",
"program":"Merian",
"RA":18.5152182914,
"propid":"2020B-0288",
"dec":-59.6086979713,
"expTime":5.0,
"count":1,
"wait":"False"
},
{
"comment":"--",
"filter":"u",
"seqtot":61,
"seqnum":16,
"seqid":"2022B",
"expType":"object",
"object":"TIC206544316_J011331.79-593353.55_u",
"proposer":"Leauthaud",
"program":"Merian",
"RA":18.3824633014,
"propid":"2020B-0288",
"dec":-59.5648765446,
"expTime":5.0,
"count":1,
"wait":"False"
},
{
"comment":"--",
"filter":"u",
"seqtot":61,
"seqnum":17,
"seqid":"2022B",
"expType":"object",
"object":"TIC206544316_J011316.72-594039.53_u",
"proposer":"Leauthaud",
"program":"Merian",
"RA":18.3196843968,
"propid":"2020B-0288",
"dec":-59.6776486445,
"expTime":5.0,
"count":1,
"wait":"False"
},
{
"comment":"--",
"filter":"u",
"seqtot":61,
"seqnum":18,
"seqid":"2022B",
"expType":"object",
"object":"TIC206544316_J011338.42-593453.68_u",
"proposer":"Leauthaud",
"program":"Merian",
"RA":18.4100889676,
"propid":"2020B-0288",
"dec":-59.5815786707,
"expTime":5.0,
"count":1,
"wait":"False"
},
{
"comment":"--",
"filter":"u",
"seqtot":61,
"seqnum":19,
"seqid":"2022B",
"expType":"object",
"object":"TIC206544316_J011357.48-593426.12_u",
"proposer":"Leauthaud",
"program":"Merian",
"RA":18.4895398688,
"propid":"2020B-0288",
"dec":-59.5739246142,
"expTime":5.0,
"count":1,
"wait":"False"
},
{
"comment":"--",
"filter":"u",
"seqtot":61,
"seqnum":20,
"seqid":"2022B",
"expType":"object",
"object":"TIC206544316_J011318.94-594436.69_u",
"proposer":"Leauthaud",
"program":"Merian",
"RA":18.3289482136,
"propid":"2020B-0288",
"dec":-59.7435252389,
"expTime":5.0,
"count":1,
"wait":"False"
},
{
"comment":"--",
"filter":"u",
"seqtot":61,
"seqnum":21,
"seqid":"2022B",
"expType":"object",
"object":"TIC206544316_J011357.19-594139.35_u",
"proposer":"Leauthaud",
"program":"Merian",
"RA":18.4883274502,
"propid":"2020B-0288",
"dec":-59.6942640923,
"expTime":5.0,
"count":1,
"wait":"False"
},
{
"comment":"--",
"filter":"u",
"seqtot":61,
"seqnum":22,
"seqid":"2022B",
"expType":"object",
"object":"TIC206544316_J011353.34-593758.37_u",
"proposer":"Leauthaud",
"program":"Merian",
"RA":18.472286897,
"propid":"2020B-0288",
"dec":-59.6328807781,
"expTime":5.0,
"count":1,
"wait":"False"
},
{
"comment":"--",
"filter":"u",
"seqtot":61,
"seqnum":23,
"seqid":"2022B",
"expType":"object",
"object":"TIC206544316_J011356.78-594146.50_u",
"proposer":"Leauthaud",
"program":"Merian",
"RA":18.4866052175,
"propid":"2020B-0288",
"dec":-59.6962516499,
"expTime":5.0,
"count":1,
"wait":"False"
},
{
"comment":"--",
"filter":"u",
"seqtot":61,
"seqnum":24,
"seqid":"2022B",
"expType":"object",
"object":"TIC206544316_J011350.41-593523.98_u",
"proposer":"Leauthaud",
"program":"Merian",
"RA":18.4600638342,
"propid":"2020B-0288",
"dec":-59.5899954833,
"expTime":5.0,
"count":1,
"wait":"False"
},
{
"comment":"--",
"filter":"u",
"seqtot":61,
"seqnum":25,
"seqid":"2022B",
"expType":"object",
"object":"TIC206544316_J011343.01-593402.32_u",
"proposer":"Leauthaud",
"program":"Merian",
"RA":18.4292491612,
"propid":"2020B-0288",
"dec":-59.5673123678,
"expTime":5.0,
"count":1,
"wait":"False"
},
{
"comment":"--",
"filter":"u",
"seqtot":61,
"seqnum":26,
"seqid":"2022B",
"expType":"object",
"object":"TIC206544316_J011350.42-593532.54_u",
"proposer":"Leauthaud",
"program":"Merian",
"RA":18.4601204525,
"propid":"2020B-0288",
"dec":-59.5923738262,
"expTime":5.0,
"count":1,
"wait":"False"
},
{
"comment":"--",
"filter":"u",
"seqtot":61,
"seqnum":27,
"seqid":"2022B",
"expType":"object",
"object":"TIC206544316_J011351.19-593407.05_u",
"proposer":"Leauthaud",
"program":"Merian",
"RA":18.4633002019,
"propid":"2020B-0288",
"dec":-59.5686268584,
"expTime":5.0,
"count":1,
"wait":"False"
},
{
"comment":"--",
"filter":"u",
"seqtot":61,
"seqnum":28,
"seqid":"2022B",
"expType":"object",
"object":"TIC206544316_J011344.08-593644.03_u",
"proposer":"Leauthaud",
"program":"Merian",
"RA":18.4337008004,
"propid":"2020B-0288",
"dec":-59.6122323082,
"expTime":5.0,
"count":1,
"wait":"False"
},
{
"comment":"--",
"filter":"u",
"seqtot":61,
"seqnum":29,
"seqid":"2022B",
"expType":"object",
"object":"TIC206544316_J011330.16-593416.94_u",
"proposer":"Leauthaud",
"program":"Merian",
"RA":18.3756903638,
"propid":"2020B-0288",
"dec":-59.5713739253,
"expTime":5.0,
"count":1,
"wait":"False"
},
{
"comment":"--",
"filter":"u",
"seqtot":61,
"seqnum":30,
"seqid":"2022B",
"expType":"object",
"object":"TIC206544316_J011355.89-593752.09_u",
"proposer":"Leauthaud",
"program":"Merian",
"RA":18.4828957791,
"propid":"2020B-0288",
"dec":-59.6311372384,
"expTime":5.0,
"count":1,
"wait":"False"
},
{
"comment":"--",
"filter":"u",
"seqtot":61,
"seqnum":31,
"seqid":"2022B",
"expType":"object",
"object":"TIC206544316_J011335.44-593748.61_u",
"proposer":"Leauthaud",
"program":"Merian",
"RA":18.397669087,
"propid":"2020B-0288",
"dec":-59.6301698178,
"expTime":5.0,
"count":1,
"wait":"False"
},
{
"comment":"--",
"filter":"u",
"seqtot":61,
"seqnum":32,
"seqid":"2022B",
"expType":"object",
"object":"TIC206544316_J011314.97-593931.28_u",
"proposer":"Leauthaud",
"program":"Merian",
"RA":18.3124033409,
"propid":"2020B-0288",
"dec":-59.6586909058,
"expTime":5.0,
"count":1,
"wait":"False"
},
{
"comment":"--",
"filter":"u",
"seqtot":61,
"seqnum":33,
"seqid":"2022B",
"expType":"object",
"object":"TIC206544316_J011351.37-594443.67_u",
"proposer":"Leauthaud",
"program":"Merian",
"RA":18.4640432155,
"propid":"2020B-0288",
"dec":-59.7454648132,
"expTime":5.0,
"count":1,
"wait":"False"
},
{
"comment":"--",
"filter":"u",
"seqtot":61,
"seqnum":34,
"seqid":"2022B",
"expType":"object",
"object":"TIC206544316_J011348.41-593720.64_u",
"proposer":"Leauthaud",
"program":"Merian",
"RA":18.451724166,
"propid":"2020B-0288",
"dec":-59.6224021024,
"expTime":5.0,
"count":1,
"wait":"False"
},
{
"comment":"--",
"filter":"u",
"seqtot":61,
"seqnum":35,
"seqid":"2022B",
"expType":"object",
"object":"TIC206544316_J011400.51-594035.97_u",
"proposer":"Leauthaud",
"program":"Merian",
"RA":18.5021639213,
"propid":"2020B-0288",
"dec":-59.6766598702,
"expTime":5.0,
"count":1,
"wait":"False"
},
{
"comment":"--",
"filter":"u",
"seqtot":61,
"seqnum":36,
"seqid":"2022B",
"expType":"object",
"object":"TIC206544316_J011329.75-594014.13_u",
"proposer":"Leauthaud",
"program":"Merian",
"RA":18.3739907889,
"propid":"2020B-0288",
"dec":-59.6705923969,
"expTime":5.0,
"count":1,
"wait":"False"
},
{
"comment":"--",
"filter":"u",
"seqtot":61,
"seqnum":37,
"seqid":"2022B",
"expType":"object",
"object":"TIC206544316_J011315.15-594407.91_u",
"proposer":"Leauthaud",
"program":"Merian",
"RA":18.3131476016,
"propid":"2020B-0288",
"dec":-59.7355329922,
"expTime":5.0,
"count":1,
"wait":"False"
},
{
"comment":"--",
"filter":"u",
"seqtot":61,
"seqnum":38,
"seqid":"2022B",
"expType":"object",
"object":"TIC206544316_J011342.37-594419.82_u",
"proposer":"Leauthaud",
"program":"Merian",
"RA":18.4265526077,
"propid":"2020B-0288",
"dec":-59.738841526,
"expTime":5.0,
"count":1,
"wait":"False"
},
{
"comment":"--",
"filter":"u",
"seqtot":61,
"seqnum":39,
"seqid":"2022B",
"expType":"object",
"object":"TIC206544316_J011325.68-593903.61_u",
"proposer":"Leauthaud",
"program":"Merian",
"RA":18.3570037928,
"propid":"2020B-0288",
"dec":-59.651003196,
"expTime":5.0,
"count":1,
"wait":"False"
},
{
"comment":"--",
"filter":"u",
"seqtot":61,
"seqnum":40,
"seqid":"2022B",
"expType":"object",
"object":"TIC206544316_J011401.16-593515.19_u",
"proposer":"Leauthaud",
"program":"Merian",
"RA":18.5048690336,
"propid":"2020B-0288",
"dec":-59.5875535234,
"expTime":5.0,
"count":1,
"wait":"False"
},
{
"comment":"--",
"filter":"u",
"seqtot":61,
"seqnum":41,
"seqid":"2022B",
"expType":"object",
"object":"TIC206544316_J011316.26-593756.82_u",
"proposer":"Leauthaud",
"program":"Merian",
"RA":18.3177699381,
"propid":"2020B-0288",
"dec":-59.6324516537,
"expTime":5.0,
"count":1,
"wait":"False"
},
{
"comment":"--",
"filter":"u",
"seqtot":61,
"seqnum":42,
"seqid":"2022B",
"expType":"object",
"object":"TIC206544316_J011321.73-593525.84_u",
"proposer":"Leauthaud",
"program":"Merian",
"RA":18.340550386,
"propid":"2020B-0288",
"dec":-59.5905120613,
"expTime":5.0,
"count":1,
"wait":"False"
},
{
"comment":"--",
"filter":"u",
"seqtot":61,
"seqnum":43,
"seqid":"2022B",
"expType":"object",
"object":"TIC206544316_J011316.31-593729.40_u",
"proposer":"Leauthaud",
"program":"Merian",
"RA":18.3179809903,
"propid":"2020B-0288",
"dec":-59.6248350174,
"expTime":5.0,
"count":1,
"wait":"False"
},
{
"comment":"--",
"filter":"u",
"seqtot":61,
"seqnum":44,
"seqid":"2022B",
"expType":"object",
"object":"TIC206544316_J011320.87-593728.28_u",
"proposer":"Leauthaud",
"program":"Merian",
"RA":18.3369990972,
"propid":"2020B-0288",
"dec":-59.6245249232,
"expTime":5.0,
"count":1,
"wait":"False"
},
{
"comment":"--",
"filter":"u",
"seqtot":61,
"seqnum":45,
"seqid":"2022B",
"expType":"object",
"object":"TIC206544316_J011327.18-594132.23_u",
"proposer":"Leauthaud",
"program":"Merian",
"RA":18.3632650709,
"propid":"2020B-0288",
"dec":-59.6922883223,
"expTime":5.0,
"count":1,
"wait":"False"
},
{
"comment":"--",
"filter":"u",
"seqtot":61,
"seqnum":46,
"seqid":"2022B",
"expType":"object",
"object":"TIC206544316_J011356.80-593738.48_u",
"proposer":"Leauthaud",
"program":"Merian",
"RA":18.4866854871,
"propid":"2020B-0288",
"dec":-59.6273573151,
"expTime":5.0,
"count":1,
"wait":"False"
},
{
"comment":"--",
"filter":"u",
"seqtot":61,
"seqnum":47,
"seqid":"2022B",
"expType":"object",
"object":"TIC206544316_J011326.62-594016.02_u",
"proposer":"Leauthaud",
"program":"Merian",
"RA":18.3609228288,
"propid":"2020B-0288",
"dec":-59.6711181208,
"expTime":5.0,
"count":1,
"wait":"False"
},
{
"comment":"--",
"filter":"u",
"seqtot":61,
"seqnum":48,
"seqid":"2022B",
"expType":"object",
"object":"TIC206544316_J011322.19-593719.01_u",
"proposer":"Leauthaud",
"program":"Merian",
"RA":18.3424891318,
"propid":"2020B-0288",
"dec":-59.6219475249,
"expTime":5.0,
"count":1,
"wait":"False"
},
{
"comment":"--",
"filter":"u",
"seqtot":61,
"seqnum":49,
"seqid":"2022B",
"expType":"object",
"object":"TIC206544316_J011400.85-593456.97_u",
"proposer":"Leauthaud",
"program":"Merian",
"RA":18.5035582916,
"propid":"2020B-0288",
"dec":-59.5824927496,
"expTime":5.0,
"count":1,
"wait":"False"
},
{
"comment":"--",
"filter":"u",
"seqtot":61,
"seqnum":50,
"seqid":"2022B",
"expType":"object",
"object":"TIC206544316_J011359.48-594416.70_u",
"proposer":"Leauthaud",
"program":"Merian",
"RA":18.4978352965,
"propid":"2020B-0288",
"dec":-59.7379730247,
"expTime":5.0,
"count":1,
"wait":"False"
},
{
"comment":"--",
"filter":"u",
"seqtot":61,
"seqnum":51,
"seqid":"2022B",
"expType":"object",
"object":"TIC206544316_J011337.24-593616.43_u",
"proposer":"Leauthaud",
"program":"Merian",
"RA":18.4051881273,
"propid":"2020B-0288",
"dec":-59.6045641001,
"expTime":5.0,
"count":1,
"wait":"False"
},
{
"comment":"--",
"filter":"u",
"seqtot":61,
"seqnum":52,
"seqid":"2022B",
"expType":"object",
"object":"TIC206544316_J011341.12-593656.52_u",
"proposer":"Leauthaud",
"program":"Merian",
"RA":18.4213440585,
"propid":"2020B-0288",
"dec":-59.6157009727,
"expTime":5.0,
"count":1,
"wait":"False"
},
{
"comment":"--",
"filter":"u",
"seqtot":61,
"seqnum":53,
"seqid":"2022B",
"expType":"object",
"object":"TIC206544316_J011327.62-594012.53_u",
"proposer":"Leauthaud",
"program":"Merian",
"RA":18.3651044903,
"propid":"2020B-0288",
"dec":-59.6701492034,
"expTime":5.0,
"count":1,
"wait":"False"
},
{
"comment":"--",
"filter":"u",
"seqtot":61,
"seqnum":54,
"seqid":"2022B",
"expType":"object",
"object":"TIC206544316_J011337.31-593610.98_u",
"proposer":"Leauthaud",
"program":"Merian",
"RA":18.4054605717,
"propid":"2020B-0288",
"dec":-59.6030502235,
"expTime":5.0,
"count":1,
"wait":"False"
},
{
"comment":"--",
"filter":"u",
"seqtot":61,
"seqnum":55,
"seqid":"2022B",
"expType":"object",
"object":"TIC206544316_J011339.43-593501.22_u",
"proposer":"Leauthaud",
"program":"Merian",
"RA":18.4143180646,
"propid":"2020B-0288",
"dec":-59.5836745977,
"expTime":5.0,
"count":1,
"wait":"False"
},
{
"comment":"--",
"filter":"u",
"seqtot":61,
"seqnum":56,
"seqid":"2022B",
"expType":"object",
"object":"TIC206544316_J011328.66-593919.81_u",
"proposer":"Leauthaud",
"program":"Merian",
"RA":18.3694403163,
"propid":"2020B-0288",
"dec":-59.6555039528,
"expTime":5.0,
"count":1,
"wait":"False"
},
{
"comment":"--",
"filter":"u",
"seqtot":61,
"seqnum":57,
"seqid":"2022B",
"expType":"object",
"object":"TIC206544316_J011357.78-593537.95_u",
"proposer":"Leauthaud",
"program":"Merian",
"RA":18.4907562257,
"propid":"2020B-0288",
"dec":-59.5938774608,
"expTime":5.0,
"count":1,
"wait":"False"
},
{
"comment":"--",
"filter":"u",
"seqtot":61,
"seqnum":58,
"seqid":"2022B",
"expType":"object",
"object":"TIC206544316_J011406.47-593604.86_u",
"proposer":"Leauthaud",
"program":"Merian",
"RA":18.5269715132,
"propid":"2020B-0288",
"dec":-59.6013526124,
"expTime":5.0,
"count":1,
"wait":"False"
},
{
"comment":"--",
"filter":"u",
"seqtot":61,
"seqnum":59,
"seqid":"2022B",
"expType":"object",
"object":"TIC206544316_J011327.89-593540.89_u",
"proposer":"Leauthaud",
"program":"Merian",
"RA":18.3662150561,
"propid":"2020B-0288",
"dec":-59.5946943055,
"expTime":5.0,
"count":1,
"wait":"False"
},
{
"comment":"--",
"filter":"u",
"seqtot":61,
"seqnum":60,
"seqid":"2022B",
"expType":"object",
"object":"TIC206544316_J011344.86-594352.28_u",
"proposer":"Leauthaud",
"program":"Merian",
"RA":18.4369570321,
"propid":"2020B-0288",
"dec":-59.7311895664,
"expTime":5.0,
"count":1,
"wait":"False"
},
{
"comment":"--",
"filter":"u",
"seqtot":61,
"seqnum":61,
"seqid":"2022B",
"expType":"object",
"object":"TIC206544316_J011327.42-594152.06_u",
"proposer":"Leauthaud",
"program":"Merian",
"RA":18.3642648187,
"propid":"2020B-0288",
"dec":-59.6977965951,
"expTime":5.0,
"count":1,
"wait":"False"
}
]