[
{
"comment":"OneMinuteFocusExposure",
"filter":"r",
"seqtot":13,
"seqnum":1,
"seqid":"2022B",
"expType":"object",
"object":"1minexp_000",
"proposer":"Leauthaud",
"program":"Merian",
"RA":344.6030656,
"propid":"2020B-0288",
"dec":-31.2366291,
"expTime":60.0,
"count":1,
"wait":"False"
},
{
"comment":"--",
"filter":"r",
"seqtot":13,
"seqnum":2,
"seqid":"2022B",
"expType":"object",
"object":"GAMA5265117_J225824.73-311411.86_r",
"proposer":"Leauthaud",
"program":"Merian",
"RA":344.6030656,
"propid":"2020B-0288",
"dec":-31.2366291,
"expTime":300.0,
"count":1,
"wait":"False"
},
{
"comment":"--",
"filter":"r",
"seqtot":13,
"seqnum":3,
"seqid":"2022B",
"expType":"object",
"object":"GAMA5265117_J225836.77-311004.95_r",
"proposer":"Leauthaud",
"program":"Merian",
"RA":344.653219906,
"propid":"2020B-0288",
"dec":-31.1680443717,
"expTime":300.0,
"count":1,
"wait":"False"
},
{
"comment":"--",
"filter":"r",
"seqtot":13,
"seqnum":4,
"seqid":"2022B",
"expType":"object",
"object":"GAMA5265117_J225834.25-311344.38_r",
"proposer":"Leauthaud",
"program":"Merian",
"RA":344.6427475408,
"propid":"2020B-0288",
"dec":-31.2289967682,
"expTime":300.0,
"count":1,
"wait":"False"
},
{
"comment":"--",
"filter":"r",
"seqtot":13,
"seqnum":5,
"seqid":"2022B",
"expType":"object",
"object":"GAMA5265117_J225810.30-311055.53_r",
"proposer":"Leauthaud",
"program":"Merian",
"RA":344.5429203794,
"propid":"2020B-0288",
"dec":-31.1820943509,
"expTime":300.0,
"count":1,
"wait":"False"
},
{
"comment":"--",
"filter":"r",
"seqtot":13,
"seqnum":6,
"seqid":"2022B",
"expType":"object",
"object":"GAMA5265117_J225820.15-311020.81_r",
"proposer":"Leauthaud",
"program":"Merian",
"RA":344.5839747156,
"propid":"2020B-0288",
"dec":-31.1724499635,
"expTime":300.0,
"count":1,
"wait":"False"
},
{
"comment":"--",
"filter":"r",
"seqtot":13,
"seqnum":7,
"seqid":"2022B",
"expType":"object",
"object":"GAMA5265117_J225800.83-311855.99_r",
"proposer":"Leauthaud",
"program":"Merian",
"RA":344.503473568,
"propid":"2020B-0288",
"dec":-31.3155536956,
"expTime":300.0,
"count":1,
"wait":"False"
},
{
"comment":"--",
"filter":"r",
"seqtot":13,
"seqnum":8,
"seqid":"2022B",
"expType":"object",
"object":"GAMA5265117_J225805.09-311529.11_r",
"proposer":"Leauthaud",
"program":"Merian",
"RA":344.5212452988,
"propid":"2020B-0288",
"dec":-31.2580873924,
"expTime":300.0,
"count":1,
"wait":"False"
},
{
"comment":"--",
"filter":"r",
"seqtot":13,
"seqnum":9,
"seqid":"2022B",
"expType":"object",
"object":"GAMA5265117_J225805.75-311441.02_r",
"proposer":"Leauthaud",
"program":"Merian",
"RA":344.5239599818,
"propid":"2020B-0288",
"dec":-31.2447303109,
"expTime":300.0,
"count":1,
"wait":"False"
},
{
"comment":"--",
"filter":"r",
"seqtot":13,
"seqnum":10,
"seqid":"2022B",
"expType":"object",
"object":"GAMA5265117_J225814.30-312024.06_r",
"proposer":"Leauthaud",
"program":"Merian",
"RA":344.559621182,
"propid":"2020B-0288",
"dec":-31.340018759,
"expTime":300.0,
"count":1,
"wait":"False"
},
{
"comment":"--",
"filter":"r",
"seqtot":13,
"seqnum":11,
"seqid":"2022B",
"expType":"object",
"object":"GAMA5265117_J225844.90-312043.18_r",
"proposer":"Leauthaud",
"program":"Merian",
"RA":344.6870950438,
"propid":"2020B-0288",
"dec":-31.3453292894,
"expTime":300.0,
"count":1,
"wait":"False"
},
{
"comment":"--",
"filter":"r",
"seqtot":13,
"seqnum":12,
"seqid":"2022B",
"expType":"object",
"object":"GAMA5265117_J225809.85-311805.35_r",
"proposer":"Leauthaud",
"program":"Merian",
"RA":344.5410778697,
"propid":"2020B-0288",
"dec":-31.3014870416,
"expTime":300.0,
"count":1,
"wait":"False"
},
{
"comment":"--",
"filter":"r",
"seqtot":13,
"seqnum":13,
"seqid":"2022B",
"expType":"object",
"object":"GAMA5265117_J225844.85-311547.66_r",
"proposer":"Leauthaud",
"program":"Merian",
"RA":344.6869131471,
"propid":"2020B-0288",
"dec":-31.2632411567,
"expTime":300.0,
"count":1,
"wait":"False"
}
]