[
{
"comment":"OneMinuteFocusExposure",
"filter":"r",
"seqtot":13,
"seqnum":1,
"seqid":"2022B",
"expType":"object",
"object":"1minexp_000",
"proposer":"Leauthaud",
"program":"Merian",
"RA":345.3551208,
"propid":"2020B-0288",
"dec":-34.2113545,
"expTime":60.0,
"count":1,
"wait":"False"
},
{
"comment":"--",
"filter":"r",
"seqtot":13,
"seqnum":2,
"seqid":"2022B",
"expType":"object",
"object":"GAMA5275222_J230125.22-341240.87_r",
"proposer":"Leauthaud",
"program":"Merian",
"RA":345.3551208,
"propid":"2020B-0288",
"dec":-34.2113545,
"expTime":300.0,
"count":1,
"wait":"False"
},
{
"comment":"--",
"filter":"r",
"seqtot":13,
"seqnum":3,
"seqid":"2022B",
"expType":"object",
"object":"GAMA5275222_J230116.94-341707.06_r",
"proposer":"Leauthaud",
"program":"Merian",
"RA":345.3206022631,
"propid":"2020B-0288",
"dec":-34.2852948977,
"expTime":300.0,
"count":1,
"wait":"False"
},
{
"comment":"--",
"filter":"r",
"seqtot":13,
"seqnum":4,
"seqid":"2022B",
"expType":"object",
"object":"GAMA5275222_J230147.43-340747.15_r",
"proposer":"Leauthaud",
"program":"Merian",
"RA":345.4476622701,
"propid":"2020B-0288",
"dec":-34.129765559,
"expTime":300.0,
"count":1,
"wait":"False"
},
{
"comment":"--",
"filter":"r",
"seqtot":13,
"seqnum":5,
"seqid":"2022B",
"expType":"object",
"object":"GAMA5275222_J230131.64-341050.57_r",
"proposer":"Leauthaud",
"program":"Merian",
"RA":345.3818569179,
"propid":"2020B-0288",
"dec":-34.1807164757,
"expTime":300.0,
"count":1,
"wait":"False"
},
{
"comment":"--",
"filter":"r",
"seqtot":13,
"seqnum":6,
"seqid":"2022B",
"expType":"object",
"object":"GAMA5275222_J230127.22-341423.17_r",
"proposer":"Leauthaud",
"program":"Merian",
"RA":345.3634389935,
"propid":"2020B-0288",
"dec":-34.2397719052,
"expTime":300.0,
"count":1,
"wait":"False"
},
{
"comment":"--",
"filter":"r",
"seqtot":13,
"seqnum":7,
"seqid":"2022B",
"expType":"object",
"object":"GAMA5275222_J230134.95-341150.17_r",
"proposer":"Leauthaud",
"program":"Merian",
"RA":345.3956454497,
"propid":"2020B-0288",
"dec":-34.1972714223,
"expTime":300.0,
"count":1,
"wait":"False"
},
{
"comment":"--",
"filter":"r",
"seqtot":13,
"seqnum":8,
"seqid":"2022B",
"expType":"object",
"object":"GAMA5275222_J230144.12-341203.08_r",
"proposer":"Leauthaud",
"program":"Merian",
"RA":345.4338429807,
"propid":"2020B-0288",
"dec":-34.2008565299,
"expTime":300.0,
"count":1,
"wait":"False"
},
{
"comment":"--",
"filter":"r",
"seqtot":13,
"seqnum":9,
"seqid":"2022B",
"expType":"object",
"object":"GAMA5275222_J230108.29-340703.90_r",
"proposer":"Leauthaud",
"program":"Merian",
"RA":345.2845828141,
"propid":"2020B-0288",
"dec":-34.1177516818,
"expTime":300.0,
"count":1,
"wait":"False"
},
{
"comment":"--",
"filter":"r",
"seqtot":13,
"seqnum":10,
"seqid":"2022B",
"expType":"object",
"object":"GAMA5275222_J230135.64-341041.16_r",
"proposer":"Leauthaud",
"program":"Merian",
"RA":345.3985164046,
"propid":"2020B-0288",
"dec":-34.1781002692,
"expTime":300.0,
"count":1,
"wait":"False"
},
{
"comment":"--",
"filter":"r",
"seqtot":13,
"seqnum":11,
"seqid":"2022B",
"expType":"object",
"object":"GAMA5275222_J230137.64-340902.30_r",
"proposer":"Leauthaud",
"program":"Merian",
"RA":345.4068391142,
"propid":"2020B-0288",
"dec":-34.150639307,
"expTime":300.0,
"count":1,
"wait":"False"
},
{
"comment":"--",
"filter":"r",
"seqtot":13,
"seqnum":12,
"seqid":"2022B",
"expType":"object",
"object":"GAMA5275222_J230102.95-341040.19_r",
"proposer":"Leauthaud",
"program":"Merian",
"RA":345.2622994621,
"propid":"2020B-0288",
"dec":-34.1778311173,
"expTime":300.0,
"count":1,
"wait":"False"
},
{
"comment":"--",
"filter":"r",
"seqtot":13,
"seqnum":13,
"seqid":"2022B",
"expType":"object",
"object":"GAMA5275222_J230129.09-341606.38_r",
"proposer":"Leauthaud",
"program":"Merian",
"RA":345.371244694,
"propid":"2020B-0288",
"dec":-34.2684416332,
"expTime":300.0,
"count":1,
"wait":"False"
}
]