[
{
"comment":"OneMinuteFocusExposure",
"filter":"r",
"seqtot":41,
"seqnum":1,
"seqid":"2022B",
"expType":"object",
"object":"1minexp_000",
"proposer":"Leauthaud",
"program":"Merian",
"RA":343.2688411,
"propid":"2020B-0288",
"dec":-33.9772443,
"expTime":60.0,
"count":1,
"wait":"False"
},
{
"comment":"--",
"filter":"r",
"seqtot":41,
"seqnum":2,
"seqid":"2022B",
"expType":"object",
"object":"GAMA5240292_J225304.52-335838.07_r",
"proposer":"Leauthaud",
"program":"Merian",
"RA":343.2688411,
"propid":"2020B-0288",
"dec":-33.9772443,
"expTime":90.0,
"count":1,
"wait":"False"
},
{
"comment":"--",
"filter":"r",
"seqtot":41,
"seqnum":3,
"seqid":"2022B",
"expType":"object",
"object":"GAMA5240292_J225306.57-335834.34_r",
"proposer":"Leauthaud",
"program":"Merian",
"RA":343.2774056163,
"propid":"2020B-0288",
"dec":-33.9762067195,
"expTime":90.0,
"count":1,
"wait":"False"
},
{
"comment":"--",
"filter":"r",
"seqtot":41,
"seqnum":4,
"seqid":"2022B",
"expType":"object",
"object":"GAMA5240292_J225330.09-335647.13_r",
"proposer":"Leauthaud",
"program":"Merian",
"RA":343.3753963389,
"propid":"2020B-0288",
"dec":-33.946425804,
"expTime":90.0,
"count":1,
"wait":"False"
},
{
"comment":"--",
"filter":"r",
"seqtot":41,
"seqnum":5,
"seqid":"2022B",
"expType":"object",
"object":"GAMA5240292_J225243.65-340117.23_r",
"proposer":"Leauthaud",
"program":"Merian",
"RA":343.1818940097,
"propid":"2020B-0288",
"dec":-34.0214551829,
"expTime":90.0,
"count":1,
"wait":"False"
},
{
"comment":"--",
"filter":"r",
"seqtot":41,
"seqnum":6,
"seqid":"2022B",
"expType":"object",
"object":"GAMA5240292_J225246.62-335302.14_r",
"proposer":"Leauthaud",
"program":"Merian",
"RA":343.1942704023,
"propid":"2020B-0288",
"dec":-33.8839279158,
"expTime":90.0,
"count":1,
"wait":"False"
},
{
"comment":"--",
"filter":"r",
"seqtot":41,
"seqnum":7,
"seqid":"2022B",
"expType":"object",
"object":"GAMA5240292_J225303.31-340344.24_r",
"proposer":"Leauthaud",
"program":"Merian",
"RA":343.2638131531,
"propid":"2020B-0288",
"dec":-34.0622899887,
"expTime":90.0,
"count":1,
"wait":"False"
},
{
"comment":"--",
"filter":"r",
"seqtot":41,
"seqnum":8,
"seqid":"2022B",
"expType":"object",
"object":"GAMA5240292_J225246.00-340000.64_r",
"proposer":"Leauthaud",
"program":"Merian",
"RA":343.1916792553,
"propid":"2020B-0288",
"dec":-34.000177917,
"expTime":90.0,
"count":1,
"wait":"False"
},
{
"comment":"--",
"filter":"r",
"seqtot":41,
"seqnum":9,
"seqid":"2022B",
"expType":"object",
"object":"GAMA5240292_J225308.67-335425.81_r",
"proposer":"Leauthaud",
"program":"Merian",
"RA":343.2861590032,
"propid":"2020B-0288",
"dec":-33.9071705038,
"expTime":90.0,
"count":1,
"wait":"False"
},
{
"comment":"--",
"filter":"r",
"seqtot":41,
"seqnum":10,
"seqid":"2022B",
"expType":"object",
"object":"GAMA5240292_J225322.28-340349.49_r",
"proposer":"Leauthaud",
"program":"Merian",
"RA":343.3428724678,
"propid":"2020B-0288",
"dec":-34.0637495477,
"expTime":90.0,
"count":1,
"wait":"False"
},
{
"comment":"--",
"filter":"r",
"seqtot":41,
"seqnum":11,
"seqid":"2022B",
"expType":"object",
"object":"GAMA5240292_J225245.68-340001.79_r",
"proposer":"Leauthaud",
"program":"Merian",
"RA":343.1903552565,
"propid":"2020B-0288",
"dec":-34.0004996833,
"expTime":90.0,
"count":1,
"wait":"False"
},
{
"comment":"--",
"filter":"r",
"seqtot":41,
"seqnum":12,
"seqid":"2022B",
"expType":"object",
"object":"GAMA5240292_J225245.39-335558.24_r",
"proposer":"Leauthaud",
"program":"Merian",
"RA":343.1891623379,
"propid":"2020B-0288",
"dec":-33.9328462547,
"expTime":90.0,
"count":1,
"wait":"False"
},
{
"comment":"--",
"filter":"r",
"seqtot":41,
"seqnum":13,
"seqid":"2022B",
"expType":"object",
"object":"GAMA5240292_J225246.34-335257.36_r",
"proposer":"Leauthaud",
"program":"Merian",
"RA":343.193092917,
"propid":"2020B-0288",
"dec":-33.8826007162,
"expTime":90.0,
"count":1,
"wait":"False"
},
{
"comment":"--",
"filter":"r",
"seqtot":41,
"seqnum":14,
"seqid":"2022B",
"expType":"object",
"object":"GAMA5240292_J225240.39-335301.40_r",
"proposer":"Leauthaud",
"program":"Merian",
"RA":343.1683286795,
"propid":"2020B-0288",
"dec":-33.8837245501,
"expTime":90.0,
"count":1,
"wait":"False"
},
{
"comment":"--",
"filter":"r",
"seqtot":41,
"seqnum":15,
"seqid":"2022B",
"expType":"object",
"object":"GAMA5240292_J225249.07-335836.82_r",
"proposer":"Leauthaud",
"program":"Merian",
"RA":343.2044946396,
"propid":"2020B-0288",
"dec":-33.976896894,
"expTime":90.0,
"count":1,
"wait":"False"
},
{
"comment":"--",
"filter":"r",
"seqtot":41,
"seqnum":16,
"seqid":"2022B",
"expType":"object",
"object":"GAMA5240292_J225301.76-335548.51_r",
"proposer":"Leauthaud",
"program":"Merian",
"RA":343.2573576122,
"propid":"2020B-0288",
"dec":-33.9301417995,
"expTime":90.0,
"count":1,
"wait":"False"
},
{
"comment":"--",
"filter":"r",
"seqtot":41,
"seqnum":17,
"seqid":"2022B",
"expType":"object",
"object":"GAMA5240292_J225258.61-335749.68_r",
"proposer":"Leauthaud",
"program":"Merian",
"RA":343.244239765,
"propid":"2020B-0288",
"dec":-33.9638012372,
"expTime":90.0,
"count":1,
"wait":"False"
},
{
"comment":"--",
"filter":"r",
"seqtot":41,
"seqnum":18,
"seqid":"2022B",
"expType":"object",
"object":"GAMA5240292_J225312.09-335707.34_r",
"proposer":"Leauthaud",
"program":"Merian",
"RA":343.3004046874,
"propid":"2020B-0288",
"dec":-33.9520390869,
"expTime":90.0,
"count":1,
"wait":"False"
},
{
"comment":"--",
"filter":"r",
"seqtot":41,
"seqnum":19,
"seqid":"2022B",
"expType":"object",
"object":"GAMA5240292_J225323.99-335253.47_r",
"proposer":"Leauthaud",
"program":"Merian",
"RA":343.3499865395,
"propid":"2020B-0288",
"dec":-33.8815202265,
"expTime":90.0,
"count":1,
"wait":"False"
},
{
"comment":"--",
"filter":"r",
"seqtot":41,
"seqnum":20,
"seqid":"2022B",
"expType":"object",
"object":"GAMA5240292_J225247.16-335617.00_r",
"proposer":"Leauthaud",
"program":"Merian",
"RA":343.1965099765,
"propid":"2020B-0288",
"dec":-33.9380559866,
"expTime":90.0,
"count":1,
"wait":"False"
},
{
"comment":"--",
"filter":"r",
"seqtot":41,
"seqnum":21,
"seqid":"2022B",
"expType":"object",
"object":"GAMA5240292_J225313.06-335401.72_r",
"proposer":"Leauthaud",
"program":"Merian",
"RA":343.3044295865,
"propid":"2020B-0288",
"dec":-33.9004778694,
"expTime":90.0,
"count":1,
"wait":"False"
},
{
"comment":"--",
"filter":"r",
"seqtot":41,
"seqnum":22,
"seqid":"2022B",
"expType":"object",
"object":"GAMA5240292_J225240.60-335513.32_r",
"proposer":"Leauthaud",
"program":"Merian",
"RA":343.1691805902,
"propid":"2020B-0288",
"dec":-33.9203673235,
"expTime":90.0,
"count":1,
"wait":"False"
},
{
"comment":"--",
"filter":"r",
"seqtot":41,
"seqnum":23,
"seqid":"2022B",
"expType":"object",
"object":"GAMA5240292_J225241.67-335551.13_r",
"proposer":"Leauthaud",
"program":"Merian",
"RA":343.1736294103,
"propid":"2020B-0288",
"dec":-33.9308696988,
"expTime":90.0,
"count":1,
"wait":"False"
},
{
"comment":"--",
"filter":"r",
"seqtot":41,
"seqnum":24,
"seqid":"2022B",
"expType":"object",
"object":"GAMA5240292_J225314.45-340221.07_r",
"proposer":"Leauthaud",
"program":"Merian",
"RA":343.310248768,
"propid":"2020B-0288",
"dec":-34.0391864636,
"expTime":90.0,
"count":1,
"wait":"False"
},
{
"comment":"--",
"filter":"r",
"seqtot":41,
"seqnum":25,
"seqid":"2022B",
"expType":"object",
"object":"GAMA5240292_J225305.12-335448.42_r",
"proposer":"Leauthaud",
"program":"Merian",
"RA":343.2713642416,
"propid":"2020B-0288",
"dec":-33.9134501601,
"expTime":90.0,
"count":1,
"wait":"False"
},
{
"comment":"--",
"filter":"r",
"seqtot":41,
"seqnum":26,
"seqid":"2022B",
"expType":"object",
"object":"GAMA5240292_J225314.62-340303.48_r",
"proposer":"Leauthaud",
"program":"Merian",
"RA":343.3109235811,
"propid":"2020B-0288",
"dec":-34.0509679756,
"expTime":90.0,
"count":1,
"wait":"False"
},
{
"comment":"--",
"filter":"r",
"seqtot":41,
"seqnum":27,
"seqid":"2022B",
"expType":"object",
"object":"GAMA5240292_J225246.22-335348.68_r",
"proposer":"Leauthaud",
"program":"Merian",
"RA":343.1926136228,
"propid":"2020B-0288",
"dec":-33.8968576399,
"expTime":90.0,
"count":1,
"wait":"False"
},
{
"comment":"--",
"filter":"r",
"seqtot":41,
"seqnum":28,
"seqid":"2022B",
"expType":"object",
"object":"GAMA5240292_J225249.69-335842.13_r",
"proposer":"Leauthaud",
"program":"Merian",
"RA":343.2070490993,
"propid":"2020B-0288",
"dec":-33.9783717772,
"expTime":90.0,
"count":1,
"wait":"False"
},
{
"comment":"--",
"filter":"r",
"seqtot":41,
"seqnum":29,
"seqid":"2022B",
"expType":"object",
"object":"GAMA5240292_J225306.10-335537.45_r",
"proposer":"Leauthaud",
"program":"Merian",
"RA":343.2754247002,
"propid":"2020B-0288",
"dec":-33.9270702802,
"expTime":90.0,
"count":1,
"wait":"False"
},
{
"comment":"--",
"filter":"r",
"seqtot":41,
"seqnum":30,
"seqid":"2022B",
"expType":"object",
"object":"GAMA5240292_J225254.66-335722.98_r",
"proposer":"Leauthaud",
"program":"Merian",
"RA":343.227773543,
"propid":"2020B-0288",
"dec":-33.9563850088,
"expTime":90.0,
"count":1,
"wait":"False"
},
{
"comment":"--",
"filter":"r",
"seqtot":41,
"seqnum":31,
"seqid":"2022B",
"expType":"object",
"object":"GAMA5240292_J225307.85-340240.25_r",
"proposer":"Leauthaud",
"program":"Merian",
"RA":343.2827146029,
"propid":"2020B-0288",
"dec":-34.0445165528,
"expTime":90.0,
"count":1,
"wait":"False"
},
{
"comment":"--",
"filter":"r",
"seqtot":41,
"seqnum":32,
"seqid":"2022B",
"expType":"object",
"object":"GAMA5240292_J225256.92-335521.94_r",
"proposer":"Leauthaud",
"program":"Merian",
"RA":343.2371838855,
"propid":"2020B-0288",
"dec":-33.9227627204,
"expTime":90.0,
"count":1,
"wait":"False"
},
{
"comment":"--",
"filter":"r",
"seqtot":41,
"seqnum":33,
"seqid":"2022B",
"expType":"object",
"object":"GAMA5240292_J225304.95-340152.06_r",
"proposer":"Leauthaud",
"program":"Merian",
"RA":343.2706525524,
"propid":"2020B-0288",
"dec":-34.0311299576,
"expTime":90.0,
"count":1,
"wait":"False"
},
{
"comment":"--",
"filter":"r",
"seqtot":41,
"seqnum":34,
"seqid":"2022B",
"expType":"object",
"object":"GAMA5240292_J225247.59-335332.58_r",
"proposer":"Leauthaud",
"program":"Merian",
"RA":343.1983111878,
"propid":"2020B-0288",
"dec":-33.892384821,
"expTime":90.0,
"count":1,
"wait":"False"
},
{
"comment":"--",
"filter":"r",
"seqtot":41,
"seqnum":35,
"seqid":"2022B",
"expType":"object",
"object":"GAMA5240292_J225311.38-335745.69_r",
"proposer":"Leauthaud",
"program":"Merian",
"RA":343.2974477437,
"propid":"2020B-0288",
"dec":-33.9626931851,
"expTime":90.0,
"count":1,
"wait":"False"
},
{
"comment":"--",
"filter":"r",
"seqtot":41,
"seqnum":36,
"seqid":"2022B",
"expType":"object",
"object":"GAMA5240292_J225253.56-335545.25_r",
"proposer":"Leauthaud",
"program":"Merian",
"RA":343.2231758185,
"propid":"2020B-0288",
"dec":-33.92923883,
"expTime":90.0,
"count":1,
"wait":"False"
},
{
"comment":"--",
"filter":"r",
"seqtot":41,
"seqnum":37,
"seqid":"2022B",
"expType":"object",
"object":"GAMA5240292_J225251.10-340038.45_r",
"proposer":"Leauthaud",
"program":"Merian",
"RA":343.2129569354,
"propid":"2020B-0288",
"dec":-34.0106814051,
"expTime":90.0,
"count":1,
"wait":"False"
},
{
"comment":"--",
"filter":"r",
"seqtot":41,
"seqnum":38,
"seqid":"2022B",
"expType":"object",
"object":"GAMA5240292_J225305.23-335900.80_r",
"proposer":"Leauthaud",
"program":"Merian",
"RA":343.271832325,
"propid":"2020B-0288",
"dec":-33.983556707,
"expTime":90.0,
"count":1,
"wait":"False"
},
{
"comment":"--",
"filter":"r",
"seqtot":41,
"seqnum":39,
"seqid":"2022B",
"expType":"object",
"object":"GAMA5240292_J225310.58-335922.59_r",
"proposer":"Leauthaud",
"program":"Merian",
"RA":343.2940974498,
"propid":"2020B-0288",
"dec":-33.9896087291,
"expTime":90.0,
"count":1,
"wait":"False"
},
{
"comment":"--",
"filter":"r",
"seqtot":41,
"seqnum":40,
"seqid":"2022B",
"expType":"object",
"object":"GAMA5240292_J225327.54-340048.91_r",
"proposer":"Leauthaud",
"program":"Merian",
"RA":343.364772892,
"propid":"2020B-0288",
"dec":-34.0135876269,
"expTime":90.0,
"count":1,
"wait":"False"
},
{
"comment":"--",
"filter":"r",
"seqtot":41,
"seqnum":41,
"seqid":"2022B",
"expType":"object",
"object":"GAMA5240292_J225310.46-340132.63_r",
"proposer":"Leauthaud",
"program":"Merian",
"RA":343.2936042749,
"propid":"2020B-0288",
"dec":-34.0257324419,
"expTime":90.0,
"count":1,
"wait":"False"
}
]