[
{
"comment":"OneMinuteFocusExposure",
"filter":"g",
"seqtot":13,
"seqnum":1,
"seqid":"2022B",
"expType":"object",
"object":"1minexp_000",
"proposer":"Leauthaud",
"program":"Merian",
"RA":344.079748,
"propid":"2020B-0288",
"dec":-30.8219773,
"expTime":60.0,
"count":1,
"wait":"False"
},
{
"comment":"--",
"filter":"g",
"seqtot":13,
"seqnum":2,
"seqid":"2022B",
"expType":"object",
"object":"GAMA5247018_J225619.13-304919.11_g",
"proposer":"Leauthaud",
"program":"Merian",
"RA":344.079748,
"propid":"2020B-0288",
"dec":-30.8219773,
"expTime":300.0,
"count":1,
"wait":"False"
},
{
"comment":"--",
"filter":"g",
"seqtot":13,
"seqnum":3,
"seqid":"2022B",
"expType":"object",
"object":"GAMA5247018_J225630.80-304438.64_g",
"proposer":"Leauthaud",
"program":"Merian",
"RA":344.1283546635,
"propid":"2020B-0288",
"dec":-30.7440676966,
"expTime":300.0,
"count":1,
"wait":"False"
},
{
"comment":"--",
"filter":"g",
"seqtot":13,
"seqnum":4,
"seqid":"2022B",
"expType":"object",
"object":"GAMA5247018_J225559.27-304754.14_g",
"proposer":"Leauthaud",
"program":"Merian",
"RA":343.9969638703,
"propid":"2020B-0288",
"dec":-30.7983742382,
"expTime":300.0,
"count":1,
"wait":"False"
},
{
"comment":"--",
"filter":"g",
"seqtot":13,
"seqnum":5,
"seqid":"2022B",
"expType":"object",
"object":"GAMA5247018_J225624.70-305426.43_g",
"proposer":"Leauthaud",
"program":"Merian",
"RA":344.10292709,
"propid":"2020B-0288",
"dec":-30.9073427218,
"expTime":300.0,
"count":1,
"wait":"False"
},
{
"comment":"--",
"filter":"g",
"seqtot":13,
"seqnum":6,
"seqid":"2022B",
"expType":"object",
"object":"GAMA5247018_J225624.14-305407.67_g",
"proposer":"Leauthaud",
"program":"Merian",
"RA":344.1005889859,
"propid":"2020B-0288",
"dec":-30.9021326974,
"expTime":300.0,
"count":1,
"wait":"False"
},
{
"comment":"--",
"filter":"g",
"seqtot":13,
"seqnum":7,
"seqid":"2022B",
"expType":"object",
"object":"GAMA5247018_J225631.44-305115.39_g",
"proposer":"Leauthaud",
"program":"Merian",
"RA":344.131029157,
"propid":"2020B-0288",
"dec":-30.8542774988,
"expTime":300.0,
"count":1,
"wait":"False"
},
{
"comment":"--",
"filter":"g",
"seqtot":13,
"seqnum":8,
"seqid":"2022B",
"expType":"object",
"object":"GAMA5247018_J225611.26-305243.64_g",
"proposer":"Leauthaud",
"program":"Merian",
"RA":344.0469328937,
"propid":"2020B-0288",
"dec":-30.8787905514,
"expTime":300.0,
"count":1,
"wait":"False"
},
{
"comment":"--",
"filter":"g",
"seqtot":13,
"seqnum":9,
"seqid":"2022B",
"expType":"object",
"object":"GAMA5247018_J225608.00-304418.57_g",
"proposer":"Leauthaud",
"program":"Merian",
"RA":344.0333514936,
"propid":"2020B-0288",
"dec":-30.7384929551,
"expTime":300.0,
"count":1,
"wait":"False"
},
{
"comment":"--",
"filter":"g",
"seqtot":13,
"seqnum":10,
"seqid":"2022B",
"expType":"object",
"object":"GAMA5247018_J225640.81-304747.70_g",
"proposer":"Leauthaud",
"program":"Merian",
"RA":344.1700575081,
"propid":"2020B-0288",
"dec":-30.7965846821,
"expTime":300.0,
"count":1,
"wait":"False"
},
{
"comment":"--",
"filter":"g",
"seqtot":13,
"seqnum":11,
"seqid":"2022B",
"expType":"object",
"object":"GAMA5247018_J225642.47-304705.18_g",
"proposer":"Leauthaud",
"program":"Merian",
"RA":344.1769651296,
"propid":"2020B-0288",
"dec":-30.7847731071,
"expTime":300.0,
"count":1,
"wait":"False"
},
{
"comment":"--",
"filter":"g",
"seqtot":13,
"seqnum":12,
"seqid":"2022B",
"expType":"object",
"object":"GAMA5247018_J225625.66-304535.25_g",
"proposer":"Leauthaud",
"program":"Merian",
"RA":344.1069364409,
"propid":"2020B-0288",
"dec":-30.759792961,
"expTime":300.0,
"count":1,
"wait":"False"
},
{
"comment":"--",
"filter":"g",
"seqtot":13,
"seqnum":13,
"seqid":"2022B",
"expType":"object",
"object":"GAMA5247018_J225621.93-305014.96_g",
"proposer":"Leauthaud",
"program":"Merian",
"RA":344.0913820925,
"propid":"2020B-0288",
"dec":-30.8374908844,
"expTime":300.0,
"count":1,
"wait":"False"
}
]